setup.py
probability_udacity/Binomialdistribution.py
probability_udacity/Gaussiandistribution.py
probability_udacity/Generaldistribution.py
probability_udacity/__init__.py
probability_udacity.egg-info/PKG-INFO
probability_udacity.egg-info/SOURCES.txt
probability_udacity.egg-info/dependency_links.txt
probability_udacity.egg-info/not-zip-safe
probability_udacity.egg-info/top_level.txt